hyperpack/__init__.py
hyperpack/abstract.py
hyperpack/benchmarks/__init__.py
hyperpack/benchmarks/datasets/__init__.py
hyperpack/benchmarks/datasets/hopper_and_turton_2000/__init__.py
hyperpack/benchmarks/datasets/hopper_and_turton_2000/C1.py
hyperpack/benchmarks/datasets/hopper_and_turton_2000/C2.py
hyperpack/benchmarks/datasets/hopper_and_turton_2000/C3.py
hyperpack/benchmarks/datasets/hopper_and_turton_2000/C4.py
hyperpack/benchmarks/datasets/hopper_and_turton_2000/C5.py
hyperpack/benchmarks/datasets/hopper_and_turton_2000/C6.py
hyperpack/benchmarks/datasets/hopper_and_turton_2000/C7.py
hyperpack/constants.py
hyperpack/exceptions.py
hyperpack/heuristics.py
hyperpack/loggers.py
hyperpack/mixins.py
hyperpack/processes.py
hyperpack/structures.py
hyperpack/utils.py
hyperpack-1.2.0.dist-info/LICENSE
hyperpack-1.2.0.dist-info/METADATA
hyperpack-1.2.0.dist-info/WHEEL
hyperpack-1.2.0.dist-info/RECORD
