Metadata-Version: 2.1
Name: hyperpack
Version: 1.2.0
Summary: A hyper-heuristic approach on solving the 2D bin packing problem
Home-page: https://github.com/AlkiviadisAleiferis/hyperpack
License: Apache-2.0
Keywords: 2d-binpacking,2DBPP,heuristics,meta-heuristics,local-search,hyper-heuristics,bin-packing,research,AI,algorithms,operations-research
Author: Alkiviadis Aleiferis
Author-email: alkiviadis.aliferis@gmail.com
Maintainer: Alkiviadis Aleiferis
Maintainer-email: alkiviadis.aliferis@gmail.com
Requires-Python: >=3.7,<4.0
Classifier: Intended Audience :: Information Technology
Classifier: Intended Audience :: Manufacturing
Classifier: Intended Audience :: Science/Research
Classifier: License :: OSI Approved :: Apache Software License
Classifier: Operating System :: OS Independent
Classifier: Programming Language :: Python :: 3
Classifier: Programming Language :: Python :: 3.7
Classifier: Programming Language :: Python :: 3.8
Classifier: Programming Language :: Python :: 3.9
Classifier: Programming Language :: Python :: 3.10
Classifier: Programming Language :: Python :: 3.11
Project-URL: Documentation, https://alkiviadisaleiferis.readthedocs.io/en/latest/
Project-URL: Repository, https://github.com/AlkiviadisAleiferis/hyperpack
